{
  "main": {
    "id": "a7eeb34cbd233876",
    "type": "split",
    "children": [
      {
        "id": "27be6ef2cef699b5",
        "type": "tabs",
        "children": [
          {
            "id": "c9e8db1d8b7c7c36",
            "type": "leaf",
            "state": {
              "type": "markdown",
              "state": {
                "file": "Recuperación.md",
                "mode": "source",
                "source": false
              },
              "icon": "lucide-file",
              "title": "Recuperación"
            },
            "group": "5b22fdb68bda8932"
          },
          {
            "id": "b4a33b0891261d20",
            "type": "leaf",
            "state": {
              "type": "markdown",
              "state": {
                "file": "Template Tarjeta.md",
                "mode": "source",
                "source": false
              },
              "icon": "lucide-file",
              "title": "Template Tarjeta"
            }
          }
        ]
      },
      {
        "id": "faff73f80f094623",
        "type": "tabs",
        "children": [
          {
            "id": "89a3925c4aa319eb",
            "type": "leaf",
            "state": {
              "type": "localgraph",
              "state": {
                "file": "Recuperación.md",
                "options": {
                  "collapse-filter": false,
                  "search": "",
                  "localJumps": 2,
                  "localBacklinks": true,
                  "localForelinks": true,
                  "localInterlinks": true,
                  "showTags": false,
                  "showAttachments": false,
                  "hideUnresolved": false,
                  "collapse-color-groups": false,
                  "colorGroups": [
                    {
                      "query": "tag:#Dudas  ",
                      "color": {
                        "a": 1,
                        "rgb": 16771681
                      }
                    },
                    {
                      "query": "tag: #falta  ",
                      "color": {
                        "a": 1,
                        "rgb": 14701138
                      }
                    },
                    {
                      "query": "tag:#Anki  ",
                      "color": {
                        "a": 1,
                        "rgb": 6324055
                      }
                    },
                    {
                      "query": "tag:#Rendido  ",
                      "color": {
                        "a": 1,
                        "rgb": 4325478
                      }
                    },
                    {
                      "query": "tag:#Índice_Materia  ",
                      "color": {
                        "a": 1,
                        "rgb": 5431473
                      }
                    },
                    {
                      "query": "tag:#no_sistematizado  ",
                      "color": {
                        "a": 1,
                        "rgb": 5419488
                      }
                    },
                    {
                      "query": "tag:#PREGUNTA_EXAMEN  ",
                      "color": {
                        "a": 1,
                        "rgb": 5395168
                      }
                    }
                  ],
                  "collapse-display": true,
                  "showArrow": true,
                  "textFadeMultiplier": -1,
                  "nodeSizeMultiplier": 1,
                  "lineSizeMultiplier": 1,
                  "collapse-forces": false,
                  "centerStrength": 0.521855287569573,
                  "repelStrength": 11.7654916512059,
                  "linkStrength": 0.849573283858998,
                  "linkDistance": 250,
                  "scale": 0.5995838000493192,
                  "close": true
                }
              },
              "icon": "lucide-git-fork",
              "title": "Gráfico de Recuperación"
            },
            "group": "5b22fdb68bda8932"
          }
        ]
      }
    ],
    "direction": "vertical"
  },
  "left": {
    "id": "bd806dbd884e8db5",
    "type": "split",
    "children": [
      {
        "id": "c9042e039fcde485",
        "type": "tabs",
        "children": [
          {
            "id": "02a412369ed7e457",
            "type": "leaf",
            "state": {
              "type": "file-explorer",
              "state": {
                "sortOrder": "alphabetical",
                "autoReveal": false
              },
              "icon": "lucide-folder-closed",
              "title": "Explorador de archivos"
            }
          },
          {
            "id": "0035f5a1d5d979f5",
            "type": "leaf",
            "state": {
              "type": "search",
              "state": {
                "query": "altura árbol",
                "matchingCase": false,
                "explainSearch": false,
                "collapseAll": false,
                "extraContext": false,
                "sortOrder": "alphabetical"
              },
              "icon": "lucide-search",
              "title": "Buscar"
            }
          },
          {
            "id": "63fd5aed666007ac",
            "type": "leaf",
            "state": {
              "type": "bookmarks",
              "state": {},
              "icon": "lucide-bookmark",
              "title": "Marcadores"
            }
          }
        ],
        "currentTab": 1
      }
    ],
    "direction": "horizontal",
    "width": 300,
    "collapsed": true
  },
  "right": {
    "id": "1e516bca1fc19a59",
    "type": "split",
    "children": [
      {
        "id": "eba4cea076c7925e",
        "type": "tabs",
        "children": [
          {
            "id": "ed143e313f7396f5",
            "type": "leaf",
            "state": {
              "type": "backlink",
              "state": {
                "collapseAll": false,
                "extraContext": false,
                "sortOrder": "alphabetical",
                "showSearch": false,
                "searchQuery": "",
                "backlinkCollapsed": false,
                "unlinkedCollapsed": true
              },
              "icon": "links-coming-in",
              "title": "Enlaces entrantes"
            }
          },
          {
            "id": "cebdfaefee6d12c0",
            "type": "leaf",
            "state": {
              "type": "outgoing-link",
              "state": {
                "linksCollapsed": false,
                "unlinkedCollapsed": true
              },
              "icon": "links-going-out",
              "title": "Enlaces salientes"
            }
          },
          {
            "id": "88e3f6be87535c31",
            "type": "leaf",
            "state": {
              "type": "tag",
              "state": {
                "sortOrder": "frequency",
                "useHierarchy": true,
                "showSearch": false,
                "searchQuery": ""
              },
              "icon": "lucide-tags",
              "title": "Etiquetas"
            }
          },
          {
            "id": "8a557d49f2417830",
            "type": "leaf",
            "state": {
              "type": "outline",
              "state": {
                "followCursor": false,
                "showSearch": false,
                "searchQuery": ""
              },
              "icon": "lucide-list",
              "title": "Esquema"
            }
          }
        ]
      }
    ],
    "direction": "horizontal",
    "width": 300,
    "collapsed": true
  },
  "left-ribbon": {
    "hiddenItems": {
      "bases:Crear nueva base": false,
      "switcher:Abrir selector rápido": false,
      "graph:Abrir vista gráfica": false,
      "canvas:Crear nuevo lienzo": false,
      "daily-notes:Abrir la nota de hoy": false,
      "templates:Insertar plantilla": false,
      "command-palette:Abrir paleta de comandos": false
    }
  },
  "active": "c9e8db1d8b7c7c36",
  "lastOpenFiles": [
    "Procesamiento de Transacciones.md",
    "Recuperación.md",
    "Unidad 2 - Transacciones.md",
    "Control de Concurrencia.md",
    "Técnicas basadas en validación.md",
    "Técnicas de Marca de tiempo.md",
    "Técnicas de Bloqueo.md",
    "Template Tarjeta.md",
    "Planificación de Transacciones.md",
    "Recuperabilidad.md",
    "Serializable - Planificaciones.md",
    "Planificación No-Serie.md",
    "Pasted image 20250905131221.png",
    "Planificación en Serie.md",
    "Pasted image 20250905131049.png",
    "Pasted image 20250905130836.png",
    "Lecturas no reproducibles.md",
    "Problemas Potenciales con transacciones concurrentes.md",
    "Pasted image 20250905130321.png",
    "Sobreescritura de datos no confirmados.md",
    "Pasted image 20250905130311.png",
    "Problemas de Actualización Temporal.md",
    "Pasted image 20250905130258.png",
    "Problemas de actualización Perdida.md",
    "Pasted image 20250905130246.png",
    "Pasted image 20250905130243.png",
    "Modelo Simplificado de BD.md",
    "Transacción - BD.md",
    "Base de Datos II.md",
    "MELI/Entrevista Meli/Principios ACID.md",
    "Durabilidad.md",
    "Isolation - Aislamiento.md",
    "Consistencia.md",
    "Estados de una Transacción.md",
    "Pasted image 20250905122856.png",
    "Pasted image 20250905103432.png",
    "Evaluación/Interpretación",
    "Evaluación",
    "Diferencia Observer - Pub"
  ]
}